scripts/__init__.py
scripts/default_config.py
scripts/script_utils.py
scripts/__pycache__/default_config.cpython-38.pyc
scripts/__pycache__/script_utils.cpython-38.pyc
torchreid/__init__.py
torchreid/version.py
torchreid/apis/__init__.py
torchreid/apis/export.py
torchreid/apis/training.py
torchreid/data/__init__.py
torchreid/data/datamanager.py
torchreid/data/sampler.py
torchreid/data/transforms.py
torchreid/data/datasets/__init__.py
torchreid/data/datasets/dataset.py
torchreid/data/datasets/image/__init__.py
torchreid/data/datasets/image/classification.py
torchreid/engine/__init__.py
torchreid/engine/builder.py
torchreid/engine/engine.py
torchreid/engine/image/__init__.py
torchreid/engine/image/am_softmax.py
torchreid/engine/image/multihead.py
torchreid/engine/image/multilabel.py
torchreid/integration/__init__.py
torchreid/integration/nncf/__init__.py
torchreid/integration/nncf/compression.py
torchreid/integration/nncf/compression_script_utils.py
torchreid/integration/nncf/config.py
torchreid/integration/nncf/engine.py
torchreid/integration/nncf/accuracy_aware_training/__init__.py
torchreid/integration/nncf/accuracy_aware_training/base_runner.py
torchreid/integration/nncf/accuracy_aware_training/runner.py
torchreid/integration/nncf/accuracy_aware_training/training_loop.py
torchreid/losses/__init__.py
torchreid/losses/am_softmax.py
torchreid/losses/asl.py
torchreid/losses/cross_entropy_loss.py
torchreid/metrics/__init__.py
torchreid/metrics/accuracy.py
torchreid/metrics/classification.py
torchreid/models/__init__.py
torchreid/models/common.py
torchreid/models/efficient_net_pytcv.py
torchreid/models/gcn.py
torchreid/models/inceptionv4_pytcv.py
torchreid/models/ml_decoder.py
torchreid/models/mobilenetv3.py
torchreid/models/model_store.py
torchreid/models/ptcv_wrapper.py
torchreid/models/q2l.py
torchreid/models/timm_wrapper.py
torchreid/models/transformer.py
torchreid/ops/__init__.py
torchreid/ops/data_parallel.py
torchreid/ops/dropout.py
otxreid-0.3.1.dist-info/LICENSE
otxreid-0.3.1.dist-info/METADATA
otxreid-0.3.1.dist-info/WHEEL
otxreid-0.3.1.dist-info/top_level.txt
otxreid-0.3.1.dist-info/RECORD
