Metadata-Version: 2.1
Name: otxreid
Version: 0.3.1
Summary: A library for deep learning object re-ID and classification in PyTorch
Home-page: https://github.com/openvinotoolkit/deep-object-reid
Author: Kaiyang Zhou, Intel Corporation
License: Apache-2.0
Keywords: Object Re-Identification,Image Classification,Deep Learning,Computer Vision
License-File: LICENSE
Requires-Dist: numpy
Requires-Dist: Pillow
Requires-Dist: six
Requires-Dist: scipy (==1.5.4)
Requires-Dist: opencv-python
Requires-Dist: matplotlib
Requires-Dist: tb-nightly
Requires-Dist: future
Requires-Dist: yacs
Requires-Dist: gdown
Requires-Dist: scikit-learn
Requires-Dist: terminaltables
Requires-Dist: pytorchcv
Requires-Dist: torch-lr-finder (==0.2.1)
Requires-Dist: onnx
Requires-Dist: torchvision (==0.9.*)
Requires-Dist: torch (==1.8.*)
Requires-Dist: optuna (==2.10.1)
Requires-Dist: timm (>=0.6.5)
Requires-Dist: addict
Requires-Dist: randaugment
Requires-Dist: ptflops
